<?xml version="1.0" encoding="utf-8"?>
<!DOCTYPE hibernate-mapping PUBLIC "-//Hibernate/Hibernate Mapping DTD 3.0//EN"
"http://hibernate.sourceforge.net/hibernate-mapping-3.0.dtd">
<!-- 
    Mapping file autogenerated by MyEclipse Persistence Tools
-->
<hibernate-mapping>
    <class name="org.panda.domain.PandaSendMessage" table="panda_send_message" catalog="panda">
        <id name="id" type="java.lang.Integer">
            <column name="id" />
            <generator class="native" />
        </id>
        <many-to-one name="pandaUserInfoByMsgReceiverUser" class="org.panda.domain.PandaUserInfo" fetch="select">
            <column name="msg_receiver_user">
                <comment>接收消息人的id</comment>
            </column>
        </many-to-one>
        <many-to-one name="pandaUserInfoByMsgSendUser" class="org.panda.domain.PandaUserInfo" fetch="select">
            <column name="msg_send_user">
                <comment>发送消息人的id</comment>
            </column>
        </many-to-one>
        <many-to-one name="pandaMessage" class="org.panda.domain.PandaMessage" fetch="select">
            <column name="msg_id" not-null="true">
                <comment>站内消息的id</comment>
            </column>
        </many-to-one>
        <property name="msgStatus" type="java.lang.Short">
            <column name="msg_status">
                <comment>消息状态0未读，1已读</comment>
            </column>
        </property>
        <property name="msgBox" type="java.lang.Integer">
            <column name="msg_box">
                <comment>消息信箱 0收件箱 1发件箱 2草稿箱 3垃圾箱</comment>
            </column>
        </property>
    </class>
</hibernate-mapping>
